{
    "Jerome": {
        "mi": 939.5000074564541,
        "recent1": 15.028172969856039,
        "recent3": 50.78323838781515,
        "recent7": 156.35787003897238
    },
    "Travis": {
        "mi": 694.2415046130598,
        "recent1": 2.0999860812852935,
        "recent3": 22.900013918714706,
        "recent7": 86.5001516145709
    },
    "Brib": {
        "mi": 1692.6018303109843,
        "recent1": 0,
        "recent3": 95.44398214427741,
        "recent7": 402.9749388570747
    },
    "Justin": {
        "mi": 1778.3327243895658,
        "recent1": 0,
        "recent3": 145.46535731329038,
        "recent7": 374.5652887139107
    },
    "Luke": {
        "mi": 161.23060079137838,
        "recent1": 0,
        "recent3": 0,
        "recent7": 9.933177741986796
    },
    "conor": {
        "mi": 25.448381452318454,
        "recent1": 0,
        "recent3": 0,
        "recent7": 0
    },
    "Brendan": {
        "mi": 40.85061987990137,
        "recent1": 0,
        "recent3": 0,
        "recent7": 0
    },
    "Tyler": {
        "mi": 113.99986578382249,
        "recent1": 0,
        "recent3": 0,
        "recent7": 0
    },
    "_meta": {
        "num_activities": 355,
        "time": "2024-03-06 22:14:15"
    }
}